ABD_model/ABD.pt
ABD_model/__init__.py
ABD_model/predict.py
ABD_model-0.3.0.dist-info/LICENSE
ABD_model-0.3.0.dist-info/METADATA
ABD_model-0.3.0.dist-info/WHEEL
ABD_model-0.3.0.dist-info/top_level.txt
ABD_model-0.3.0.dist-info/RECORD
