Metadata-Version: 2.2
Name: ABD-model
Version: 0.3.0
Summary: YOLO-based model for atom and bond detection in molecular images.
Home-page: https://github.com/Safi-ullah-majid/ABD-model
Author: Safi Ullah Majid
Author-email: Safeullahmaid@gmail.com
Classifier: Programming Language :: Python :: 3
Classifier: License :: OSI Approved :: MIT License
Classifier: Operating System :: OS Independent
Requires-Python: >=3.6
License-File: LICENSE
Requires-Dist: torch
Requires-Dist: opencv-python
Requires-Dist: numpy
Requires-Dist: matplotlib
Dynamic: author
Dynamic: author-email
Dynamic: classifier
Dynamic: description
Dynamic: description-content-type
Dynamic: home-page
Dynamic: requires-dist
Dynamic: requires-python
Dynamic: summary
